[
    {
        "id": "4263462d-a919-4404-b425-f71d7a140810",
        "confidence": 0.8646,
        "class": "bird",
        "target": {
            "selector": {
                "type": "RECTANGLE",
                "geometry": {
                    "bounds": {
                        "minX": 603.99695,
                        "minY": 1489.16602,
                        "maxX": 1138.55872,
                        "maxY": 2557.69507
                    },
                    "x": 603.99695,
                    "y": 1489.16602,
                    "w": 534.56177,
                    "h": 1068.5290500000003
                }
            }
        }
    }
]