[
    {
        "id": "532af2b8-84d1-4270-9a70-90b3a6a9e8ee",
        "confidence": 0.82371,
        "class": "person",
        "target": {
            "selector": {
                "type": "RECTANGLE",
                "geometry": {
                    "bounds": {
                        "minX": 533.14362,
                        "minY": 593.60242,
                        "maxX": 634.44116,
                        "maxY": 674.00281
                    },
                    "x": 533.14362,
                    "y": 593.60242,
                    "w": 101.29753999999991,
                    "h": 80.4003899999999
                }
            }
        }
    }
]